odoo/addons/request_document/README.rst
odoo/addons/request_document/__init__.py
odoo/addons/request_document/__manifest__.py
odoo/addons/request_document/data/request_order_data.xml
odoo/addons/request_document/i18n/request_document.pot
odoo/addons/request_document/models/__init__.py
odoo/addons/request_document/models/request_document.py
odoo/addons/request_document/models/request_order.py
odoo/addons/request_document/readme/CONTRIBUTORS.rst
odoo/addons/request_document/readme/DESCRIPTION.rst
odoo/addons/request_document/security/ir.model.access.csv
odoo/addons/request_document/security/request_order_security.xml
odoo/addons/request_document/static/description/icon.png
odoo/addons/request_document/static/description/index.html
odoo/addons/request_document/tests/__init__.py
odoo/addons/request_document/tests/request_document_tester.py
odoo/addons/request_document/tests/test_request_document.py
odoo/addons/request_document/views/request_document_view.xml
odoo/addons/request_document/views/request_menuitem.xml
odoo/addons/request_document/views/request_order_view.xml
odoo/addons/request_document/views/res_config_settings_views.xml
odoo_addon_request_document-18.0.2.0.1.dist-info/METADATA
odoo_addon_request_document-18.0.2.0.1.dist-info/WHEEL
odoo_addon_request_document-18.0.2.0.1.dist-info/top_level.txt
odoo_addon_request_document-18.0.2.0.1.dist-info/RECORD
